shotpointscraper.py
shotpointscraper-0.0.5.dist-info/METADATA
shotpointscraper-0.0.5.dist-info/WHEEL
shotpointscraper-0.0.5.dist-info/entry_points.txt
shotpointscraper-0.0.5.dist-info/top_level.txt
shotpointscraper-0.0.5.dist-info/RECORD
