Metadata-Version: 2.1
Name: shotpointscraper
Version: 0.0.5
Summary: A package for scrap shot data from Understats
Home-page: UNKNOWN
Author: Daiki Azuma
Author-email: s1922052@stu.musashino-u.ac.jp
License: UNKNOWN
Project-URL: shot_point_scraper, https://github.com/DaikiAzuma/shot_point_scraper
Platform: UNKNOWN
Classifier: Programming Language :: Python :: 3
Classifier: License :: OSI Approved :: MIT License
Classifier: Operating System :: OS Independent
Requires-Python: >=3.9
